{
  "default_workspace_padding": 4,
  "default_container_padding": 4,
  "global_work_area_offset": {
    "top": 52,
    "bottom": 52,
    "left": 0,
    "right": 0
  },
  "border_colours": {
    "single": "#c594ff",
    "stack": "#acc79b",
    "monocle": "#c79987",
    "unfocused": "#2b213c",
    "floating": "#acc79b"
  },
  "stackbar": {
    "height": 40,
    "mode": "OnStack",
    "tabs": {
      "width": 300,
      "focused_text": "#acc79b",
      "unfocused_text": "#998bad",
      "background": "#2b213c"
    }
  }
}
